MMonitor/__init__.py
MMonitor/mmonitor/__init__.py
MMonitor/mmonitor/monitor.py
MMonitor/quantity/__init__.py
MMonitor/quantity/quantity.py
MMonitor/quantity/multistep/__init__.py
MMonitor/quantity/multistep/base_class.py
MMonitor/quantity/multistep/mean_tid.py
MMonitor/quantity/multistep/var_tid.py
MMonitor/quantity/multistep/weight_param_jump.py
MMonitor/quantity/singlestep/__init__.py
MMonitor/quantity/singlestep/attention_save.py
MMonitor/quantity/singlestep/backward_input_mean.py
MMonitor/quantity/singlestep/backward_input_norm.py
MMonitor/quantity/singlestep/backward_input_std.py
MMonitor/quantity/singlestep/backward_output_mean.py
MMonitor/quantity/singlestep/backward_output_norm.py
MMonitor/quantity/singlestep/backward_output_std.py
MMonitor/quantity/singlestep/base_class.py
MMonitor/quantity/singlestep/forward_input_cov_condition.py
MMonitor/quantity/singlestep/forward_input_cov_condition20.py
MMonitor/quantity/singlestep/forward_input_cov_condition50.py
MMonitor/quantity/singlestep/forward_input_cov_condition80.py
MMonitor/quantity/singlestep/forward_input_cov_max_eig.py
MMonitor/quantity/singlestep/forward_input_cov_stable_rank.py
MMonitor/quantity/singlestep/forward_input_mean.py
MMonitor/quantity/singlestep/forward_input_norm.py
MMonitor/quantity/singlestep/forward_input_std.py
MMonitor/quantity/singlestep/forward_output_grad_norm.py
MMonitor/quantity/singlestep/forward_output_mean.py
MMonitor/quantity/singlestep/forward_output_std.py
MMonitor/quantity/singlestep/linear_dead_neuron_num.py
MMonitor/quantity/singlestep/res_ratio1_save.py
MMonitor/quantity/singlestep/res_ratio2_save.py
MMonitor/quantity/singlestep/weight_mean.py
MMonitor/quantity/singlestep/weight_norm.py
MMonitor/quantity/singlestep/weight_std.py
MMonitor/quantity/singlestep/zero_activation_precentage.py
MMonitor/quantity/utils/__init__.py
MMonitor/quantity/utils/calculation.py
MMonitor/utils/__init__.py
MMonitor/utils/check.py
MMonitor/utils/loader.py
MMonitor/utils/register.py
MMonitor_Mindspore-7.0.0.dist-info/METADATA
MMonitor_Mindspore-7.0.0.dist-info/WHEEL
MMonitor_Mindspore-7.0.0.dist-info/top_level.txt
MMonitor_Mindspore-7.0.0.dist-info/RECORD
