Metadata-Version: 2.1
Name: MMonitor-Mindspore
Version: 7.0.0
Summary: A Toolkit for understanding the training of neural network
Home-page: https://openi.pcl.ac.cn/wec/MMonitor
License: MIT
Classifier: Development Status :: 3 - Alpha
Classifier: Intended Audience :: Science/Research
Classifier: License :: OSI Approved :: MIT License
Classifier: Programming Language :: Python :: 3.8
Classifier: Topic :: Scientific/Engineering :: Artificial Intelligence
Requires-Dist: wandb
Requires-Dist: plotly
Requires-Dist: seaborn
Requires-Dist: transformers
Requires-Dist: einops
Requires-Dist: mindspore
